LICENSE.rst
MANIFEST.in
README.rst
jsoncatalogue.py
setup.py
tox.ini
jsoncatalogue.egg-info/PKG-INFO
jsoncatalogue.egg-info/SOURCES.txt
jsoncatalogue.egg-info/dependency_links.txt
jsoncatalogue.egg-info/not-zip-safe
jsoncatalogue.egg-info/top_level.txt
tests/test_catalogue.py
tests/data/brokencatalogue/http/google.com/broken.json
tests/data/brokencatalogue/http/wordnik.github.io/schemas/v1.2/apiDeclaration.json
tests/data/brokencatalogue/http/wordnik.github.io/schemas/v1.2/authorizationObject.json
tests/data/brokencatalogue/http/wordnik.github.io/schemas/v1.2/dataType.json
tests/data/brokencatalogue/http/wordnik.github.io/schemas/v1.2/dataTypeBase.json
tests/data/brokencatalogue/http/wordnik.github.io/schemas/v1.2/infoObject.json
tests/data/brokencatalogue/http/wordnik.github.io/schemas/v1.2/modelsObject.json
tests/data/brokencatalogue/http/wordnik.github.io/schemas/v1.2/oauth2GrantType.json
tests/data/brokencatalogue/http/wordnik.github.io/schemas/v1.2/operationObject.json
tests/data/brokencatalogue/http/wordnik.github.io/schemas/v1.2/parameterObject.json
tests/data/brokencatalogue/http/wordnik.github.io/schemas/v1.2/resourceListing.json
tests/data/brokencatalogue/http/wordnik.github.io/schemas/v1.2/resourceObject.json
tests/data/catalogue/http/wordnik.github.io/schemas/v1.2/apiDeclaration.json
tests/data/catalogue/http/wordnik.github.io/schemas/v1.2/authorizationObject.json
tests/data/catalogue/http/wordnik.github.io/schemas/v1.2/dataType.json
tests/data/catalogue/http/wordnik.github.io/schemas/v1.2/dataTypeBase.json
tests/data/catalogue/http/wordnik.github.io/schemas/v1.2/infoObject.json
tests/data/catalogue/http/wordnik.github.io/schemas/v1.2/modelsObject.json
tests/data/catalogue/http/wordnik.github.io/schemas/v1.2/oauth2GrantType.json
tests/data/catalogue/http/wordnik.github.io/schemas/v1.2/operationObject.json
tests/data/catalogue/http/wordnik.github.io/schemas/v1.2/parameterObject.json
tests/data/catalogue/http/wordnik.github.io/schemas/v1.2/resourceListing.json
tests/data/catalogue/http/wordnik.github.io/schemas/v1.2/resourceObject.json