Metadata-Version: 1.0
Name: jsoncatalogue
Version: 0.1.1
Summary: Local filesystem based JSON catalogue, usable e.g. with package `jsonschema`
Home-page: https://bitbucket.org/vlcinsky/sh-jsoncatalogue
Author: Jan Vlcinsky
Author-email: jan.vlcinsky@cdv.cz
License: MIT
Platform: UNKNOWN
